README.md
setup.py
gorilla_career_api.egg-info/PKG-INFO
gorilla_career_api.egg-info/SOURCES.txt
gorilla_career_api.egg-info/dependency_links.txt
gorilla_career_api.egg-info/requires.txt
gorilla_career_api.egg-info/top_level.txt
gorillacareer/__init__.py
gorillacareer/constants.py
gorillacareer/jobPostFinder.py
gorillacareer/utils.py