Metadata-Version: 2.1
Name: gorilla-career-api
Version: 0.1
Summary: API for getting job postings
Classifier: Programming Language :: Python :: 3
Requires-Python: >=3.7
